SHREK_pkg/__init__.py
shrek-0.0.2.dist-info/LICENSE
shrek-0.0.2.dist-info/METADATA
shrek-0.0.2.dist-info/WHEEL
shrek-0.0.2.dist-info/top_level.txt
shrek-0.0.2.dist-info/RECORD
