Metadata-Version: 2.1
Name: shrek
Version: 0.0.2
Summary: A package for scATAC-seq pre-processing
Home-page: https://github.com/mvinyard/shrek
Author: Michael E. Vinyard
Author-email: mvinyard@mgh.harvard.com
License: UNKNOWN
Platform: UNKNOWN
Classifier: Programming Language :: Python :: 3
Classifier: License :: OSI Approved :: MIT License
Classifier: Operating System :: OS Independent
